llamate/__init__.py
llamate/agent.py
llamate/backends.py
llamate/cli.py
llamate/config.py
llamate/embedder.py
llamate/store.py
llamate/utils.py
llamate/vectorstore_postgres.py
llamate/commands/init.py
llamate-0.1.16.dist-info/licenses/LICENSE
llamate-0.1.16.dist-info/METADATA
llamate-0.1.16.dist-info/WHEEL
llamate-0.1.16.dist-info/entry_points.txt
llamate-0.1.16.dist-info/top_level.txt
llamate-0.1.16.dist-info/RECORD
