Metadata-Version: 2.4
Name: llamate
Version: 0.1.16
Summary: A memory-augmented framework for LLMs
Author: Andy Thompson
Author-email: Andy Thompson <andyt338@gmail.com>
License: MIT
Project-URL: Homepage, https://github.com/andyt338/llamate
Project-URL: Bug Tracker, https://github.com/andyt338/llamate/issues
Requires-Python: >=3.8
License-File: LICENSE
Requires-Dist: openai>=1.0.0
Requires-Dist: python-dotenv
Requires-Dist: psycopg2-binary
Provides-Extra: dev
Requires-Dist: pytest; extra == "dev"
Dynamic: author
Dynamic: license-file
Dynamic: requires-python
